mustiolo/__init__.py
mustiolo/cli.py
mustiolo/exception.py
mustiolo/message_box.py
mustiolo/utils.py
mustiolo/models/__init__.py
mustiolo/models/command.py
mustiolo/models/function_info.py
mustiolo/models/parameters.py
mustiolo-0.5.1.dist-info/licenses/LICENSE
mustiolo-0.5.1.dist-info/METADATA
mustiolo-0.5.1.dist-info/WHEEL
mustiolo-0.5.1.dist-info/top_level.txt
mustiolo-0.5.1.dist-info/RECORD
