Metadata-Version: 2.4
Name: mustiolo
Version: 0.5.1
Summary: A lightweight Python framework for building command-line interfaces (CLI).
Author-email: Alessandro Pischedda <alessandro.pischedda@gmail.com>
License: MIT
Project-URL: Homepage, https://github.com/Cereal84/mustiolo
Keywords: cli,command-line,framework,python
Classifier: Programming Language :: Python :: 3
Classifier: License :: OSI Approved :: MIT License
Classifier: Operating System :: OS Independent
Requires-Python: >=3.11
License-File: LICENSE
Dynamic: license-file
